gaik/__init__.py
gaik/_version.py
gaik/py.typed
gaik/software_components/__init__.py
gaik/software_components/config.py
gaik/software_components/RAG/README.md
gaik/software_components/RAG/__init__.py
gaik/software_components/RAG/answer_generator/README.md
gaik/software_components/RAG/answer_generator/__init__.py
gaik/software_components/RAG/answer_generator/generator.py
gaik/software_components/RAG/embedder/README.md
gaik/software_components/RAG/embedder/__init__.py
gaik/software_components/RAG/embedder/embedder.py
gaik/software_components/RAG/rag_parser_docling/README.md
gaik/software_components/RAG/rag_parser_docling/__init__.py
gaik/software_components/RAG/rag_parser_docling/parser.py
gaik/software_components/RAG/rag_parser_vision/README.md
gaik/software_components/RAG/rag_parser_vision/__init__.py
gaik/software_components/RAG/rag_parser_vision/parser.py
gaik/software_components/RAG/retriever/README.md
gaik/software_components/RAG/retriever/__init__.py
gaik/software_components/RAG/retriever/retriever.py
gaik/software_components/RAG/vector_store/README.md
gaik/software_components/RAG/vector_store/__init__.py
gaik/software_components/RAG/vector_store/vector_store.py
gaik/software_components/doc_classifier/README.md
gaik/software_components/doc_classifier/__init__.py
gaik/software_components/doc_classifier/classifier.py
gaik/software_components/extractor/README.md
gaik/software_components/extractor/__init__.py
gaik/software_components/extractor/extractor.py
gaik/software_components/extractor/schema.py
gaik/software_components/extractor/schema_basic.py
gaik/software_components/extractor/Architectures/.gitkeep
gaik/software_components/extractor/requirements/.gitkeep
gaik/software_components/extractor/tests/.gitkeep
gaik/software_components/parsers/README.md
gaik/software_components/parsers/__init__.py
gaik/software_components/parsers/docling.py
gaik/software_components/parsers/docx_parser.py
gaik/software_components/parsers/pymypdf.py
gaik-0.3.6.dist-info/licenses/LICENSE
gaik-0.3.6.dist-info/METADATA
gaik-0.3.6.dist-info/WHEEL
gaik-0.3.6.dist-info/top_level.txt
gaik-0.3.6.dist-info/RECORD
