Metadata-Version: 2.4
Name: gaik
Version: 0.3.6
Summary: General AI Kit - Reusable AI/ML components for Python
Author: GAIK Project
License: MIT License
Project-URL: Homepage, https://gaik.ai/
Project-URL: Repository, https://github.com/GAIK-project/gaik-toolkit
Project-URL: Documentation, https://github.com/GAIK-project/gaik-toolkit/tree/main/docs
Project-URL: Issues, https://github.com/GAIK-project/gaik-toolkit/issues
Keywords: ai,ml,openai,azure-openai,structured-outputs,pydantic,schema,extraction,transcription,whisper,audio,video,pdf-parsing
Classifier: Development Status :: 3 - Alpha
Classifier: Intended Audience :: Developers
Classifier: License :: OSI Approved :: MIT License
Classifier: Programming Language :: Python :: 3
Classifier: Programming Language :: Python :: 3.11
Classifier: Programming Language :: Python :: 3.12
Classifier: Topic :: Software Development :: Libraries :: Python Modules
Classifier: Topic :: Scientific/Engineering :: Artificial Intelligence
Requires-Python: >=3.11
License-File: LICENSE
Requires-Dist: pydantic>=2.12.0
Requires-Dist: python-dotenv>=1.2.0
Requires-Dist: openai>=2.7.0
Provides-Extra: extract
Provides-Extra: embedder
Requires-Dist: openai>=1.58.0; extra == "embedder"
Requires-Dist: langchain-core>=0.2.0; extra == "embedder"
Provides-Extra: vector-store
Requires-Dist: langchain-core>=0.2.0; extra == "vector-store"
Requires-Dist: numpy>=1.24.0; extra == "vector-store"
Requires-Dist: chromadb>=0.5.0; extra == "vector-store"
Provides-Extra: retriever
Requires-Dist: gaik[embedder]; extra == "retriever"
Requires-Dist: gaik[vector-store]; extra == "retriever"
Requires-Dist: langchain-core>=0.2.0; extra == "retriever"
Requires-Dist: sentence-transformers>=2.6.0; extra == "retriever"
Provides-Extra: answer-generator
Requires-Dist: openai>=1.58.0; extra == "answer-generator"
Requires-Dist: langchain-core>=0.2.0; extra == "answer-generator"
Provides-Extra: parser
Requires-Dist: PyMuPDF>=1.26.0; extra == "parser"
Requires-Dist: python-docx>=1.2.0; extra == "parser"
Requires-Dist: docling==2.64.1; extra == "parser"
Requires-Dist: psutil; extra == "parser"
Provides-Extra: rag-parser-docling
Requires-Dist: docling==2.64.1; extra == "rag-parser-docling"
Requires-Dist: docling-core[chunking]<3.0.0,>=2.50.1; extra == "rag-parser-docling"
Requires-Dist: docling-ibm-models<4,>=3.9.1; extra == "rag-parser-docling"
Requires-Dist: docling-parse<5.0.0,>=4.7.0; extra == "rag-parser-docling"
Requires-Dist: langchain-core>=0.2.0; extra == "rag-parser-docling"
Requires-Dist: pydantic>=2.0.0; extra == "rag-parser-docling"
Requires-Dist: python-dotenv>=1.0.0; extra == "rag-parser-docling"
Requires-Dist: torch>=2.1.0; extra == "rag-parser-docling"
Requires-Dist: transformers>=4.39.0; extra == "rag-parser-docling"
Provides-Extra: rag-parser-vision
Requires-Dist: docling==2.64.1; extra == "rag-parser-vision"
Requires-Dist: docling-core[chunking]<3.0.0,>=2.50.1; extra == "rag-parser-vision"
Requires-Dist: docling-ibm-models<4,>=3.9.1; extra == "rag-parser-vision"
Requires-Dist: docling-parse<5.0.0,>=4.7.0; extra == "rag-parser-vision"
Requires-Dist: langchain-core>=0.2.0; extra == "rag-parser-vision"
Requires-Dist: openai>=2.7; extra == "rag-parser-vision"
Requires-Dist: PyMuPDF>=1.23.0; extra == "rag-parser-vision"
Requires-Dist: Pillow>=10.0.0; extra == "rag-parser-vision"
Requires-Dist: pydantic>=2.0.0; extra == "rag-parser-vision"
Requires-Dist: python-dotenv>=1.0.0; extra == "rag-parser-vision"
Requires-Dist: torch>=2.1.0; extra == "rag-parser-vision"
Requires-Dist: transformers>=4.39.0; extra == "rag-parser-vision"
Provides-Extra: rag-workflow
Requires-Dist: gaik[rag-parser-vision]; extra == "rag-workflow"
Requires-Dist: gaik[embedder]; extra == "rag-workflow"
Requires-Dist: gaik[vector-store]; extra == "rag-workflow"
Requires-Dist: gaik[retriever]; extra == "rag-workflow"
Requires-Dist: gaik[answer-generator]; extra == "rag-workflow"
Provides-Extra: transcriber
Requires-Dist: pydub>=0.25.1; extra == "transcriber"
Provides-Extra: classifier
Requires-Dist: PyMuPDF>=1.26.0; extra == "classifier"
Requires-Dist: python-docx>=1.2.0; extra == "classifier"
Provides-Extra: all
Requires-Dist: gaik[extract]; extra == "all"
Requires-Dist: gaik[parser]; extra == "all"
Requires-Dist: gaik[transcriber]; extra == "all"
Requires-Dist: gaik[classifier]; extra == "all"
Requires-Dist: gaik[rag-parser-docling]; extra == "all"
Requires-Dist: gaik[rag-parser-vision]; extra == "all"
Requires-Dist: gaik[embedder]; extra == "all"
Requires-Dist: gaik[vector-store]; extra == "all"
Requires-Dist: gaik[retriever]; extra == "all"
Requires-Dist: gaik[answer-generator]; extra == "all"
Requires-Dist: gaik[rag-workflow]; extra == "all"
Requires-Dist: gaik[audio-to-structured-data]; extra == "all"
Requires-Dist: gaik[documents-to-structured-data]; extra == "all"
Provides-Extra: audio-to-structured-data
Requires-Dist: gaik[transcriber]; extra == "audio-to-structured-data"
Requires-Dist: gaik[extract]; extra == "audio-to-structured-data"
Provides-Extra: documents-to-structured-data
Requires-Dist: gaik[parser]; extra == "documents-to-structured-data"
Requires-Dist: gaik[extract]; extra == "documents-to-structured-data"
Provides-Extra: parser-cpu
Requires-Dist: PyMuPDF>=1.26.0; extra == "parser-cpu"
Requires-Dist: python-docx>=1.2.0; extra == "parser-cpu"
Provides-Extra: documents-to-structured-data-cpu
Requires-Dist: gaik[parser-cpu]; extra == "documents-to-structured-data-cpu"
Requires-Dist: gaik[extract]; extra == "documents-to-structured-data-cpu"
Provides-Extra: all-cpu
Requires-Dist: gaik[extract]; extra == "all-cpu"
Requires-Dist: gaik[parser-cpu]; extra == "all-cpu"
Requires-Dist: gaik[transcriber]; extra == "all-cpu"
Requires-Dist: gaik[classifier]; extra == "all-cpu"
Requires-Dist: gaik[audio-to-structured-data]; extra == "all-cpu"
Requires-Dist: gaik[documents-to-structured-data-cpu]; extra == "all-cpu"
Requires-Dist: gaik[rag-workflow]; extra == "all-cpu"
Provides-Extra: dev
Requires-Dist: ruff>=0.14.1; extra == "dev"
Requires-Dist: build>=1.0; extra == "dev"
Requires-Dist: twine>=4.0; extra == "dev"
Requires-Dist: pytest>=8.0; extra == "dev"
Dynamic: license-file
